encrypt/__init__.py
encrypt/atenc.py
encrypt/cmd.py
encrypt/encrypt_helper.py
aoe_tool-0.0.3.dist-info/LICENSE
aoe_tool-0.0.3.dist-info/METADATA
aoe_tool-0.0.3.dist-info/WHEEL
aoe_tool-0.0.3.dist-info/entry_points.txt
aoe_tool-0.0.3.dist-info/top_level.txt
aoe_tool-0.0.3.dist-info/RECORD
