Metadata-Version: 2.1
Name: aoe-tool
Version: 0.0.3
Summary: aoe tools.
Home-page: https://github.com/didi/AoE
Author: zouyuefu
Author-email: zouyf_1984@163.com
License: UNKNOWN
Platform: UNKNOWN
Classifier: Programming Language :: Python :: 3
Classifier: License :: OSI Approved :: Apache Software License
Classifier: Operating System :: OS Independent
Requires-Python: >=3.6
